{
  "condition": "full_abc",
  "n_params": 38773249,
  "final_train_loss": 0.5244982707500457,
  "final_train_ppl": 1.689610908464932,
  "final_val_loss": 0.8288823301166031,
  "final_val_ppl": 2.2907569988324576,
  "avg_tok_per_sec": 779.9536972197664,
  "max_steps": 1000,
  "n_stages": 4,
  "flops_per_step": 50877726720,
  "n_forward_passes": 5,
  "tokenizer": {
    "type": "bpe",
    "vocab_size": 50262,
    "max_seq_len": 256
  },
  "warmstart": {
    "checkpoint_path": "../results/v4.0_scaleup/baseline_1000/seed_42/baseline_model.pt",
    "warmstart_from_condition": "baseline",
    "target_condition": "full_abc"
  },
  "train_history": [
    {
      "step": 50,
      "loss": 0.8115117406845093,
      "ppl": 2.2513088105692076,
      "tok_per_sec": 2036.1559842547135,
      "stage": 0,
      "lr": 0.0003
    },
    {
      "step": 100,
      "loss": 0.8033505403995513,
      "ppl": 2.2330101993435307,
      "tok_per_sec": 2340.038278203698,
      "stage": 0,
      "lr": 0.0002982315288144571
    },
    {
      "step": 150,
      "loss": 0.8180252349376679,
      "ppl": 2.266020557997234,
      "tok_per_sec": 1927.4826885774246,
      "stage": 0,
      "lr": 0.0002928295870007162
    },
    {
      "step": 200,
      "loss": 0.7525808942317963,
      "ppl": 2.12247082649834,
      "tok_per_sec": 2263.411673996227,
      "stage": 0,
      "lr": 0.0002839407872804591
    },
    {
      "step": 250,
      "loss": 0.7466161197423935,
      "ppl": 2.1098484488996747,
      "tok_per_sec": 2035.221879172679,
      "stage": 0,
      "lr": 0.0002718075929386829
    },
    {
      "step": 300,
      "loss": 1.267981561422348,
      "ppl": 3.55367244892101,
      "tok_per_sec": 1089.3895500410417,
      "stage": 1,
      "lr": 0.00025676096588815437
    },
    {
      "step": 350,
      "loss": 0.7426578527688981,
      "ppl": 2.1015136121023574,
      "tok_per_sec": 926.4442631270585,
      "stage": 1,
      "lr": 0.0002392113388911824
    },
    {
      "step": 400,
      "loss": 0.7083191394805908,
      "ppl": 2.0305752747437693,
      "tok_per_sec": 1028.7465539170737,
      "stage": 1,
      "lr": 0.00021963742002378123
    },
    {
      "step": 450,
      "loss": 0.6930405658483505,
      "ppl": 1.9997867819431032,
      "tok_per_sec": 917.3812743531332,
      "stage": 1,
      "lr": 0.0001985731347672554
    },
    {
      "step": 500,
      "loss": 0.6598044353723526,
      "ppl": 1.9344139944557401,
      "tok_per_sec": 1042.2894675934058,
      "stage": 1,
      "lr": 0.0001765930619129093
    },
    {
      "step": 550,
      "loss": 0.7898422682285309,
      "ppl": 2.203048908042427,
      "tok_per_sec": 839.3127450757593,
      "stage": 2,
      "lr": 0.00015429676055043592
    },
    {
      "step": 600,
      "loss": 0.6574173194169998,
      "ppl": 1.9298018310199132,
      "tok_per_sec": 928.2822362807267,
      "stage": 2,
      "lr": 0.00013229241565888386
    },
    {
      "step": 650,
      "loss": 0.6405283719301224,
      "ppl": 1.897483191341044,
      "tok_per_sec": 814.1023166579071,
      "stage": 2,
      "lr": 0.00011118024840584842
    },
    {
      "step": 700,
      "loss": 0.58876174390316,
      "ppl": 1.8017559981812195,
      "tok_per_sec": 938.3481298305725,
      "stage": 2,
      "lr": 9.153614367868e-05
    },
    {
      "step": 750,
      "loss": 0.5815387892723084,
      "ppl": 1.7887888831678527,
      "tok_per_sec": 838.4354563220166,
      "stage": 2,
      "lr": 7.389594144597647e-05
    },
    {
      "step": 800,
      "loss": 0.6891114038228988,
      "ppl": 1.991944712130971,
      "tok_per_sec": 871.5141468169093,
      "stage": 3,
      "lr": 5.874082044007091e-05
    },
    {
      "step": 850,
      "loss": 0.5520042324066162,
      "ppl": 1.7367303432547658,
      "tok_per_sec": 712.0287906744073,
      "stage": 3,
      "lr": 4.648417285555234e-05
    },
    {
      "step": 900,
      "loss": 0.5727373319864273,
      "ppl": 1.773114016243556,
      "tok_per_sec": 775.1096377308469,
      "stage": 3,
      "lr": 3.746032808783081e-05
    },
    {
      "step": 950,
      "loss": 0.5207979094982147,
      "ppl": 1.6833702911187778,
      "tok_per_sec": 717.9220573719256,
      "stage": 3,
      "lr": 3.191543309876209e-05
    },
    {
      "step": 1000,
      "loss": 0.5244982707500457,
      "ppl": 1.689610908464932,
      "tok_per_sec": 823.193853504743,
      "stage": 3,
      "lr": 3.0000738169185534e-05
    }
  ],
  "val_history": [
    {
      "step": 100,
      "val_loss": 0.9554908687406315,
      "val_ppl": 2.5999465022047024,
      "stage": 0
    },
    {
      "step": 200,
      "val_loss": 0.9218469582739268,
      "val_ppl": 2.51392922713436,
      "stage": 0
    },
    {
      "step": 300,
      "val_loss": 0.974671446403329,
      "val_ppl": 2.6502963035377833,
      "stage": 1
    },
    {
      "step": 400,
      "val_loss": 0.8882761499705266,
      "val_ppl": 2.4309354690779315,
      "stage": 1
    },
    {
      "step": 500,
      "val_loss": 0.8698639304267651,
      "val_ppl": 2.386586089678828,
      "stage": 1
    },
    {
      "step": 600,
      "val_loss": 0.85194532426344,
      "val_ppl": 2.3442026535339227,
      "stage": 2
    },
    {
      "step": 700,
      "val_loss": 0.8314056460219845,
      "val_ppl": 2.2965446013068,
      "stage": 2
    },
    {
      "step": 800,
      "val_loss": 0.8645435633906094,
      "val_ppl": 2.3739222936120186,
      "stage": 3
    },
    {
      "step": 900,
      "val_loss": 0.8265759997202486,
      "val_ppl": 2.285479844105734,
      "stage": 3
    },
    {
      "step": 1000,
      "val_loss": 0.8288823301166031,
      "val_ppl": 2.2907569988324576,
      "stage": 3
    }
  ]
}